cortecx/__init__.py
cortecx/architecture/__init__.py
cortecx/architecture/build.py
cortecx/constrcution/__init__.py
cortecx/constrcution/foundation.py
cortecx/constrcution/materials.py
Cortecx-0.0.1.dist-info/LICENSE
Cortecx-0.0.1.dist-info/METADATA
Cortecx-0.0.1.dist-info/WHEEL
Cortecx-0.0.1.dist-info/entry_points.txt
Cortecx-0.0.1.dist-info/top_level.txt
Cortecx-0.0.1.dist-info/RECORD
