Metadata-Version: 2.1
Name: Cortecx
Version: 0.0.1
Summary: Cortecx is a Deep Learning ToolKit
Home-page: UNKNOWN
Author: Lleyton Ariton
Author-email: lleyton.ariton@gmail.com
License: MIT
Keywords: artificial intelligence
Platform: UNKNOWN
